mom_encrypter/__init__.py
mom_encrypter/encrypter.py
MomwhyareyouhereEncrypter-0.8.dist-info/METADATA
MomwhyareyouhereEncrypter-0.8.dist-info/WHEEL
MomwhyareyouhereEncrypter-0.8.dist-info/top_level.txt
MomwhyareyouhereEncrypter-0.8.dist-info/RECORD
