Metadata-Version: 2.1
Name: MomwhyareyouhereEncrypter
Version: 0.8
Summary: A Encrypter
Home-page: https://github.com/Momwhyareyouhere/MomwhyareyouhereEncrypter
Author: Momwhyareyouhere
Author-email: momwhyareyouherebusiness@gmail.com
